{
    "id": "1d03fa75-567e-45fa-9bf9-63333d4f3ba4",
    "offsetX": 0,
    "offsetY": 0,
    "zoom": 100,
    "gridSize": 0,
    "links": [
        {
            "id": "b8bc04b9-8503-4688-a69c-a96b9b0d90d3",
            "type": "default",
            "selected": false,
            "source": "572181cd-2927-4612-a1b6-caa6ae9b6e31",
            "sourcePort": "750fef5b-d1ff-4e17-8f81-f76de5dc95b8",
            "target": "ecb5f112-cf7f-4bbe-bca0-5a483a31b33d",
            "targetPort": "d1cb86be-97f6-4eea-b1a0-4f432317fb03",
            "points": [
                {
                    "id": "4bb7df76-3113-4381-a621-bce3e0848e2f",
                    "selected": false,
                    "x": 0,
                    "y": 0
                },
                {
                    "id": "7d373608-6fa1-4ac2-99d7-60913f18676f",
                    "selected": false,
                    "x": 0,
                    "y": 0
                }
            ],
            "extras": {},
            "labels": [],
            "width": 3,
            "color": "rgba(255,255,255,0.5)",
            "curvyness": 50
        }
    ],
    "nodes": [
        {
            "id": "572181cd-2927-4612-a1b6-caa6ae9b6e31",
            "type": "task",
            "selected": false,
            "x": 100,
            "y": 150,
            "extras": {},
            "ports": [
                {
                    "id": "3aa0de82-39fd-4750-8eb0-50caf816b69b",
                    "type": "default",
                    "selected": false,
                    "name": "e980ddd3-6149-421b-b839-0b2e3c2c38b2",
                    "parentNode": "572181cd-2927-4612-a1b6-caa6ae9b6e31",
                    "links": [],
                    "in": true,
                    "label": " "
                },
                {
                    "id": "750fef5b-d1ff-4e17-8f81-f76de5dc95b8",
                    "type": "default",
                    "selected": false,
                    "name": "d7f9fac0-3ae0-4709-9be3-63b06ae931b0",
                    "parentNode": "572181cd-2927-4612-a1b6-caa6ae9b6e31",
                    "links": [
                        "b8bc04b9-8503-4688-a69c-a96b9b0d90d3"
                    ],
                    "in": false,
                    "label": " "
                }
            ],
            "name": "Create",
            "color": "#31363F"
        },
        {
            "id": "ecb5f112-cf7f-4bbe-bca0-5a483a31b33d",
            "type": "task",
            "selected": false,
            "x": 350,
            "y": 150,
            "extras": {},
            "ports": [
                {
                    "id": "d1cb86be-97f6-4eea-b1a0-4f432317fb03",
                    "type": "default",
                    "selected": false,
                    "name": "3d032239-4af0-4ea0-9d6c-a12b2e0c637a",
                    "parentNode": "ecb5f112-cf7f-4bbe-bca0-5a483a31b33d",
                    "links": [
                        "b8bc04b9-8503-4688-a69c-a96b9b0d90d3"
                    ],
                    "in": true,
                    "label": " "
                }
            ],
            "name": "Migrate",
            "color": "#31363F"
        }
    ]
}